slack_bulkdelete/__init__.py
slack_bulkdelete-1.1.0.dist-info/DESCRIPTION.rst
slack_bulkdelete-1.1.0.dist-info/METADATA
slack_bulkdelete-1.1.0.dist-info/RECORD
slack_bulkdelete-1.1.0.dist-info/WHEEL
slack_bulkdelete-1.1.0.dist-info/entry_points.txt
slack_bulkdelete-1.1.0.dist-info/metadata.json
slack_bulkdelete-1.1.0.dist-info/top_level.txt
