Metadata-Version: 2.0
Name: slack-bulkdelete
Version: 1.1.0
Summary: keep your team under the file upload limit
Home-page: https://gitlab.com/pleasantone/slack-bulkdelete
Author: Paul Traina
Author-email: bulk+pypi@pst.org
License: UNKNOWN
Platform: UNKNOWN
Classifier: Development Status :: 5 - Production/Stable
Classifier: Environment :: Console
Classifier: License :: OSI Approved :: GNU Affero General Public License v3 or later (AGPLv3+)
Classifier: Natural Language :: English
Classifier: Operating System :: POSIX
Classifier: Programming Language :: Python :: 3.4
Classifier: Programming Language :: Python :: 3.5
Classifier: Topic :: Communications :: Chat
Classifier: Topic :: Office/Business :: Groupware
Requires-Dist: slacker
Provides-Extra: dev
Requires-Dist: check-manifest; extra == 'dev'
Provides-Extra: test
Requires-Dist: coverage; extra == 'test'
